hjc236_covid_dashboard/__init__.py
hjc236_covid_dashboard/config_handler.py
hjc236_covid_dashboard/conftest.py
hjc236_covid_dashboard/covid_data_handler.py
hjc236_covid_dashboard/covid_news_handling.py
hjc236_covid_dashboard/main.py
hjc236_covid_dashboard/time_conversions.py
hjc236_covid_dashboard-1.52.dist-info/LICENSE.txt
hjc236_covid_dashboard-1.52.dist-info/METADATA
hjc236_covid_dashboard-1.52.dist-info/WHEEL
hjc236_covid_dashboard-1.52.dist-info/top_level.txt
hjc236_covid_dashboard-1.52.dist-info/RECORD
