Metadata-Version: 2.1
Name: hjc236-covid-dashboard
Version: 1.52
Summary: A python project which generates a web dashboard with COVID-19 data and relevant news articles.
Home-page: https://github.com/hjc236/hjc236_covid_dashboard/
Author: hjc236
Author-email: 
License: UNKNOWN
Platform: UNKNOWN
Classifier: Operating System :: OS Independent
Classifier: License :: OSI Approved :: MIT License
Classifier: Programming Language :: Python :: 3
Requires-Python: >=3.9
License-File: LICENSE.txt
